vicradcal/__init__.py
vicradcal/constants/__init__.py
vicradcal/constants/bayer_pattern.py
vicradcal/constants/camera_specs.py
vicradcal/constants/dark_boundaries.py
vicradcal/constants/filter_boundaries.py
vicradcal/constants/flatfield_regions.py
vicradcal/constants/radiance_cal.py
vicradcal/dirtools/__init__.py
vicradcal/dirtools/condense_fits.py
vicradcal/dirtools/ITSweep_configuration_example.yaml
vicradcal/dirtools/ITSweep_configuration_template.yaml
vicradcal/dirtools/save_flatfield.py
vicradcal/dirtools/save_it_sweep.py
vicradcal/dirtools/sweep_config.py
vicradcal/DSS_Spectra_As-run_consolidated_2025cal.xlsx
vicradcal/io/__init__.py
vicradcal/io/array2fits.py
vicradcal/io/dat2fits.py
vicradcal/io/read_dat.py
vicradcal/io/read_fits.py
vicradcal/masking/__init__.py
vicradcal/masking/colormask.py
vicradcal/masking/filtermask.py
vicradcal/masking/flatfieldmask.py
vicradcal/metadata/__init__.py
vicradcal/metadata/CalibrationMetadata.py
vicradcal/metadata/get_metadata.py
vicradcal/metadata/templates.py
vicradcal/parse_dss_config.py
vicradcal/ptc/__init__.py
vicradcal/ptc/build_curve_full_filter.py
vicradcal/ptc/build_curve_pixelbypixel.py
vicradcal/ptc/get_mean_variance.py
vicradcal/utils/__init__.py
vicradcal/utils/get_filepaths.py
vicradcal/utils/get_options_errors.py
vicradcal/utils/linear_fitting.py
vicradcal/utils/mc_variance_error.py
vicradcal/utils/show_filter_map.py
vicradcal-0.0.1.dist-info/LICENSE
vicradcal-0.0.1.dist-info/METADATA
vicradcal-0.0.1.dist-info/WHEEL
vicradcal-0.0.1.dist-info/RECORD
