Metadata-Version: 2.3
Name: vicradcal
Version: 0.0.1
Summary: Pipeline code for the Lunar-VISE, Visible Infrared Camera (VIC) system ground calibration.
Author: Zachary M. Vig
Author-email: zvig@umd.edu
Requires-Python: >=3.13
Classifier: Programming Language :: Python :: 3
Classifier: Programming Language :: Python :: 3.13
Requires-Dist: astropy (>=7.1.0,<8.0.0)
Requires-Dist: numpy (>=2.3.2,<3.0.0)
Requires-Dist: pyyaml (>=6.0.2,<7.0.0)
Requires-Dist: tqdm (>=4.67.1,<5.0.0)
